xtract/__init__.py
xtract/__main__.py
xtract/base.py
xtract/types.py
xtract/utils.py
xtract/version.py
xtract-0.1a3.dist-info/DESCRIPTION.rst
xtract-0.1a3.dist-info/METADATA
xtract-0.1a3.dist-info/RECORD
xtract-0.1a3.dist-info/WHEEL
xtract-0.1a3.dist-info/entry_points.txt
xtract-0.1a3.dist-info/metadata.json
xtract-0.1a3.dist-info/top_level.txt
