Metadata-Version: 2.0
Name: xtract
Version: 0.1a3
Summary: Library to (un)pack archives and (de)compress files
Home-page: https://rolln.de/knoppo/xtract
Author: Mathias Stelzer
Author-email: knoppo@rolln.de
License: GNU GPLv3+
Keywords: xtract extract unpack pack archive compress decompress zip rar tar gz gzip bz bzip bz2 bzip2 xzmagic python-magic
Platform: UNKNOWN
Classifier: Development Status :: 3 - Alpha
Classifier: Intended Audience :: Developers
Classifier: Topic :: System :: Archiving
Classifier: Topic :: System :: Archiving :: Compression
Classifier: License :: OSI Approved :: GNU General Public License v3 or later (GPLv3+)
Classifier: Programming Language :: Python :: 2
Classifier: Programming Language :: Python :: 2.7
Classifier: Programming Language :: Python :: 3
Classifier: Programming Language :: Python :: 3.4
Classifier: Programming Language :: Python :: 3.5
Classifier: Programming Language :: Python :: 3.6
Requires-Dist: python-magic
